china_region/__init__.py
china_region/constants.py
china_region/core.py
china_region/region.csv
china_region-0.0.11.dist-info/LICENSE
china_region-0.0.11.dist-info/METADATA
china_region-0.0.11.dist-info/WHEEL
china_region-0.0.11.dist-info/top_level.txt
china_region-0.0.11.dist-info/RECORD
