Metadata-Version: 2.1
Name: china-region
Version: 0.0.11
Summary: 中国地区邮编经纬度/工具.
Home-page: https://github.com/sfyc23/China-zip-code-latitude-and-longitude
Author: sfyc23
Author-email: sfyc23@gmail.com
License: MIT
Keywords: China,zipCode,latitude,longitude
Platform: UNKNOWN
Classifier: License :: OSI Approved :: MIT License
Classifier: Operating System :: MacOS
Classifier: Operating System :: Microsoft
Classifier: Operating System :: POSIX
Classifier: Operating System :: Unix
Classifier: Programming Language :: Python
Classifier: Programming Language :: Python :: 3
Classifier: Programming Language :: Python :: 3.6
Classifier: Programming Language :: Python :: Implementation :: CPython
Classifier: Programming Language :: Python :: Implementation :: PyPy
Requires-Python: >=3.6.0
Requires-Dist: pandas (>=0.23.4)
